{
    "code": [],
    "collection": [],
    "componentModules": [],
    "description": [],
    "distributorPartNumber": [],
    "eagleBoard": [],
    "eagleSchem": [],
    "footprintEagle": [],
    "footprintEagleDetails": [],
    "footprintKicad": [
        "FOOTPRINT-kicad-kicad-footprints-Connector_JST-JST_SH_BM11B-SRSS-TB_1x11-1MP_P1.00mm_Vertical"
    ],
    "footprintKicadDetails": [],
    "gitName": [],
    "gitRepo": [],
    "hexID": [
        "HSH11"
    ],
    "kicadBoard": [],
    "kicadSchem": [],
    "manufacturerPartNumber": [
        {
            "DESCRIPTION": "",
            "LINK": "",
            "MANUCODE": "C-JSTSAL",
            "MANUFACTURER": "Japan Solderless Terminals",
            "MPN": "BM11B-SRSS-TB",
            "MPNKEY": "MPN-C-JSTSAL-BM11B-SRSS-TB",
            "OOMPID": "HEAD-JSTSH-X-PI11-SM",
            "OOMPIDPARTIAL": "HEAD-JSTSH-X-PI11-SM",
            "TAGS": []
        },
        {
            "DESCRIPTION": "",
            "LINK": "",
            "MANUCODE": "C-JSTSAL",
            "MANUFACTURER": "Japan Solderless Terminals",
            "MPN": "BM11B-SRSS-TB",
            "MPNKEY": "MPN-C-JSTSAL-BM11B-SRSS-TB",
            "OOMPID": "HEAD-JSTSH-X-PI11-SM",
            "OOMPIDPARTIAL": "HEAD-JSTSH-X-PI11-SM",
            "TAGS": []
        }
    ],
    "matchSpecial": [],
    "matchingBlock": [],
    "name": [
        "JST SH (1 mm) 11 Pin Header (SMD)"
    ],
    "oompColor": [
        "X"
    ],
    "oompDesc": [
        "PI11"
    ],
    "oompID": [
        "HEAD-JSTSH-X-PI11-SM"
    ],
    "oompIndex": [
        "SM"
    ],
    "oompInstances": [],
    "oompNote": [],
    "oompParts": [],
    "oompSize": [
        "JSTSH"
    ],
    "oompType": [
        "HEAD"
    ],
    "oplPartNumber": [],
    "rawParts": [],
    "symbolEagle": [],
    "symbolEagleDetails": [],
    "symbolKicad": [
        "SYMBOL-kicad-kicad-symbols-Connector-Conn_01x11_Male",
        "SYMBOL-kicad-kicad-symbols-Connector_Generic-Conn_01x11"
    ],
    "symbolKicadDetails": [],
    "tags": []
}